MANIFEST.in
README.md
setup.py
madt/madt_DataIndex.py
madt/madt_LibCheck.py
madt/madt_LibMap.py
madt.egg-info/PKG-INFO
madt.egg-info/SOURCES.txt
madt.egg-info/dependency_links.txt
madt.egg-info/entry_points.txt
madt.egg-info/requires.txt
madt.egg-info/top_level.txt