Metadata-Version: 2.1
Name: madt
Version: 0.0.1
Summary: Processing open-source amplicon database for ecology
Author: Yufei Zeng
Author-email: yfzeng0827@hotmail.com
Keywords: python,bioinformatic,amplicon,ecology
